{
    "$schema": "http://json-schema.org/draft-04/schema#",
    "type": "object",
    "properties": {
      "statusCode": {
        "type": "string"
      },
      "statusDesc": {
        "type": "string"
      },
      "data": {
        "type": "array",
        "items":
          {
            "type": "object",
            "properties": {
              "durationFrom": {
                "type": "number"
              },
              "durationTo": {
                "type": "number"
              },
              "durationUnit": {
                "type": "string"
              },
              "billCycleValue":{
                "type": "number"
              },
              "billCycleUnit":{
                "type": "string"
              },
              "internetUsageType": {
                "type": "string"
              },
              "internetNetworkCoverage":{
                "type": "string"
              },
              "internetQuotaType": {
                "type": "string"
              },
              "internetSpeed": {
                "type": "string"
              },
              "fixedSpeedPriceTypePattern":{
                "type":"string"
              },
              "fixedSpeedFromTiming":{
                "type":"string"
              },
              "fixedSpeedToTiming":{
                "type":"string"
              },
              "internetThrottlingSpeed": {
                "type": "string"
              },
              "internetExceedRateExcVat":{
                "type":"number"
              },
              "internetExceedRateExcVatUnit":{
                "type":"string"
              },
              "internetExceedRateIncVat":{
                "type":"number"
              },
              "internetExceedRateIncVatUnit":{
                "type":"string"
              },
              "internetQuotaFromTiming": {
                "type": "string"
              },
              "internetQuotaToTiming": {
                "type": "string"
              },
              "internetQuotaNetworkCoverage": {
                "type": "string"
              },
              "internetQuota": {
                "type": "number"
              },
              "internetQuotaUnit": {
                "type": "string"
              },
              "internetQuotaNextG": {
                "type": ["string"],
                "enum": ["Y", "N"]
              },
              "internetQuotaBlockBit": {
                "type": ["string"],
                "enum": ["Y", "N"]
              },
              "internetQuotaRollOver": {
                "type": ["string"],
                "enum": ["Y", "N"]
              },
              "maxRollOverQuota":{
                "type":"number"
              },
              "maxRollOverQuotaUnit":{
                "type":"string"
              }
            },
            "required": [
              "durationFrom",
              "durationTo",
              "durationUnit"
            ]
          }
      }
    },
    "required": [
      "statusCode",
      "statusDesc",
      "data"
    ]
  }